ab
cmd
demo
doc
