Metadata-Version: 2.4
Name: nn-dataset
Version: 2.1.2
Summary: Neural Network Dataset
Author-email: ABrain One and contributors <AI@ABrain.one>
License: MIT License
Project-URL: Homepage, https://ABrain.one
Project-URL: Repository, https://github.com/ABrain-One/nn-dataset
Project-URL: Bug Tracker, https://github.com/ABrain-One/nn-dataset/issues
Keywords: neural network,dataset,experiment archive,hyperparameters,autoML,LLM integration,model validation,benchmarking,python library,AI research
Classifier: Programming Language :: Python :: 3
Classifier: License :: OSI Approved :: MIT License
Classifier: Operating System :: OS Independent
Classifier: Topic :: Scientific/Engineering :: Artificial Intelligence
Classifier: Topic :: Software Development :: Libraries
Classifier: Intended Audience :: Developers
Classifier: Intended Audience :: Science/Research
Requires-Python: >=3.10
License-File: LICENSE
Requires-Dist: torch>=2.6.0
Requires-Dist: torchvision>=0.21.0
Requires-Dist: transformers
Requires-Dist: accelerate
Requires-Dist: diffusers
Requires-Dist: ftfy
Requires-Dist: tqdm
Requires-Dist: onnx
Requires-Dist: optuna
Requires-Dist: datasets>=3.2.0
Requires-Dist: pycocotools~=2.0.8
Requires-Dist: numpy
Requires-Dist: pandas
Requires-Dist: scipy
Requires-Dist: scikit-learn
Requires-Dist: requests>=2.32.3
Requires-Dist: pillow
Requires-Dist: setuptools
Requires-Dist: nltk>=3.9.1
Requires-Dist: evaluate
Requires-Dist: gdown
Requires-Dist: flake8~=7.1.1
Requires-Dist: flake8-json~=24.4.0
Requires-Dist: radon~=6.0.1
Requires-Dist: pylint~=3.3.3
Provides-Extra: stat
Requires-Dist: nn-stat; extra == "stat"
Dynamic: license-file
